snp_manager/__init__.py
snp_manager/snp_manager.py
snp_manager-0.1.2.dist-info/LICENSE
snp_manager-0.1.2.dist-info/METADATA
snp_manager-0.1.2.dist-info/WHEEL
snp_manager-0.1.2.dist-info/top_level.txt
snp_manager-0.1.2.dist-info/RECORD
