Metadata-Version: 2.1
Name: snp_manager
Version: 0.1.2
Summary: Read the README
Home-page: https://github.com/ShashankRaoCoding/SNP_Manager
Author: Shashank Rao
Author-email: shashankrao.websites@gmail.com
License: LGPL-3.0-or-later
Classifier: Programming Language :: Python :: 3
Classifier: License :: OSI Approved :: GNU Lesser General Public License v3 (LGPLv3)
Classifier: Operating System :: OS Independent
Requires-Python: >=3.6
License-File: LICENSE
